{
  "global": {
    "5": {
      "value": "0.5",
      "type": "opacity"
    },
    "25": {
      "value": "0.25",
      "type": "opacity"
    },
    "75": {
      "value": "0.75",
      "type": "opacity"
    },
    "space": {
      "xxxs": {
        "value": "4",
        "type": "spacing"
      },
      "xxs": {
        "value": "6",
        "type": "spacing"
      },
      "xs": {
        "value": "12",
        "type": "spacing"
      },
      "sm": {
        "value": "20",
        "type": "spacing"
      },
      "md": {
        "value": "24",
        "type": "spacing"
      },
      "lg": {
        "value": "36",
        "type": "spacing"
      },
      "xl": {
        "value": "48",
        "type": "spacing"
      },
      "xxl": {
        "value": "60",
        "type": "spacing"
      }
    },
    "palette": {
      "primary": {
        "value": "#7373E5",
        "type": "color"
      },
      "black": {
        "value": "#000000",
        "type": "color"
      },
      "greyDark": {
        "value": "#102040",
        "type": "color"
      },
      "grey": {
        "value": "#475266",
        "type": "color"
      },
      "greyLight": {
        "value": "#7D8FB2",
        "type": "color"
      },
      "whiteOff": {
        "value": "#F7F9FC",
        "type": "color"
      },
      "white": {
        "value": "#FFFFFFF",
        "type": "color"
      },
      "blue": {
        "value": "#00AAFF",
        "type": "color"
      },
      "green": {
        "value": "#52CCA3",
        "type": "color"
      },
      "red": {
        "value": "#E57399",
        "type": "color"
      },
      "yellow": {
        "value": "#FFB266",
        "type": "color"
      },
      "transparent": {
        "value": "rgba(0, 0, 0, 0)",
        "type": "color"
      },
      "border": {
        "value": "#EBEFF7",
        "type": "color"
      },
      "disabled": {
        "value": "#DAE2F2",
        "type": "color"
      },
      "toggle": {
        "value": "#B8C7E5",
        "type": "color"
      }
    },
    "badge": {
      "default": {
        "value": "{palette.greyLight}",
        "type": "color"
      },
      "primary": {
        "value": "{palette.primary}",
        "type": "color"
      },
      "danger": {
        "value": "{palette.red}",
        "type": "color"
      },
      "info": {
        "value": "{palette.blue}",
        "type": "color"
      },
      "warning": {
        "value": "{palette.yellow}",
        "type": "color"
      },
      "success": {
        "value": "{palette.green}",
        "type": "color"
      }
    },
    "button": {
      "tertiary": {
        "value": "{palette.blue}",
        "type": "color"
      },
      "background": {
        "primary": {
          "value": "{palette.primary}",
          "type": "color"
        },
        "secondary": {
          "value": "{palette.greyLight}",
          "type": "color"
        },
        "tertiary": {
          "value": "{palette.transparent}",
          "type": "color"
        },
        "tertiaryHover": {
          "value": "{palette.whiteOff}",
          "type": "color"
        },
        "outline": {
          "value": "{palette.transparent}",
          "type": "color"
        },
        "disabled": {
          "value": "{palette.disabled}",
          "type": "color"
        }
      }
    },
    "input": {
      "background": {
        "default": {
          "value": "{palette.whiteOff}",
          "type": "color"
        },
        "light": {
          "value": "{palette.white}",
          "type": "color"
        },
        "focus": {
          "value": "{palette.white}",
          "type": "color"
        },
        "disabled": {
          "value": "{palette.disabled}",
          "type": "color"
        }
      },
      "border": {
        "default": {
          "value": "{palette.border}",
          "type": "color"
        },
        "focus": {
          "value": "{palette.blue}",
          "type": "color"
        }
      }
    },
    "toggle": {
      "background": {
        "default": {
          "value": "{palette.border}",
          "type": "color"
        },
        "hover": {
          "value": "{palette.disabled}",
          "type": "color"
        },
        "active": {
          "value": "{palette.white}",
          "type": "color"
        },
        "disabled": {
          "value": "{palette.disabled}",
          "type": "color"
        }
      },
      "border": {
        "default": {
          "value": "{palette.toggle}",
          "type": "color"
        },
        "focus": {
          "value": "{palette.blue}88",
          "type": "color"
        },
        "active": {
          "value": "{palette.blue}",
          "type": "color"
        }
      }
    },
    "text": {
      "default": {
        "value": "{palette.grey}",
        "type": "color"
      },
      "secondary": {
        "value": "{palette.greyLight}",
        "type": "color"
      },
      "bold": {
        "value": "{palette.greyDark}",
        "type": "color"
      },
      "link": {
        "value": "{palette.blue}",
        "type": "color"
      },
      "reversed": {
        "value": "{palette.white}",
        "type": "color"
      },
      "primary": {
        "value": "{palette.primary}",
        "type": "color"
      }
    },
    "default": {
      "value": "720",
      "type": "sizing"
    },
    "card": {
      "value": "320",
      "type": "sizing"
    },
    "wide": {
      "value": "1312",
      "type": "sizing"
    },
    "grid": {
      "value": "1440",
      "type": "sizing"
    },
    "aside": {
      "value": "256",
      "type": "sizing"
    },
    "radii": {
      "xs": {
        "value": "4",
        "type": "borderRadius"
      },
      "sm": {
        "value": "8",
        "type": "borderRadius"
      },
      "md": {
        "value": "16",
        "type": "borderRadius"
      },
      "lg": {
        "value": "32",
        "type": "borderRadius"
      },
      "full": {
        "value": "9999",
        "type": "borderRadius"
      }
    },
    "body": {
      "value": "Inter, -apple-system, BlinkMacSystemFont, \"Segoe UI\", Roboto, Oxygen, Ubuntu, Cantarell, \"Open Sans\", \"Helvetica Neue\", sans-serif",
      "type": "fontFamilies"
    },
    "heading": {
      "value": "Inter, -apple-system, BlinkMacSystemFont, \"Segoe UI\", Roboto, Oxygen, Ubuntu, Cantarell, \"Open Sans\", \"Helvetica Neue\", sans-serif",
      "type": "fontFamilies"
    },
    "fontSizes": {
      "0": {
        "value": "0.75rem",
        "type": "fontSizes"
      },
      "1": {
        "value": "0.875rem",
        "type": "fontSizes"
      },
      "2": {
        "value": "1rem",
        "type": "fontSizes"
      },
      "3": {
        "value": "1.125rem",
        "type": "fontSizes"
      },
      "4": {
        "value": "1.25rem",
        "type": "fontSizes"
      },
      "5": {
        "value": "1.5rem",
        "type": "fontSizes"
      },
      "6": {
        "value": "2.25rem",
        "type": "fontSizes"
      }
    }
  }
}